iosautomationdriver/__init__.py
iosautomationdriver/usbdevicedetector.py
iosautomationdriver/utils.py
iosautomationdriver/webdriveragent.py
iosautomationdrivercli-0.1.data/scripts/iosautomationdrivercli
iosautomationdrivercli-0.1.dist-info/METADATA
iosautomationdrivercli-0.1.dist-info/WHEEL
iosautomationdrivercli-0.1.dist-info/top_level.txt
iosautomationdrivercli-0.1.dist-info/RECORD
