Metadata-Version: 2.1
Name: iosautomationdrivercli
Version: 0.1
Summary: __pip_description__
Home-page: UNKNOWN
Author: handyTool
Author-email: tomcat1991@126.com
License: MIT
Platform: UNKNOWN
Classifier: Programming Language :: Python :: 3
Classifier: License :: OSI Approved :: MIT License
Classifier: Operating System :: OS Independent
Requires-Dist: coloredlogs
Requires-Dist: events
Requires-Dist: requests
Requires-Dist: grequests
Requires-Dist: pyudev
